build/lib/build/lib/build/lib/docs/conf.py
build/lib/build/lib/build/lib/gdaps_frontend_vue/__init__.py
build/lib/build/lib/build/lib/gdaps_frontend_vue/webpack.py
build/lib/build/lib/build/lib/tests/__init__.py
build/lib/build/lib/build/lib/tests/conftest.py
build/lib/build/lib/build/lib/tests/test_settings.py
build/lib/build/lib/build/lib/tests/test_vueengine.py
build/lib/build/lib/docs/conf.py
build/lib/build/lib/gdaps_frontend_vue/__init__.py
build/lib/build/lib/gdaps_frontend_vue/webpack.py
build/lib/build/lib/tests/__init__.py
build/lib/build/lib/tests/conftest.py
build/lib/build/lib/tests/test_settings.py
build/lib/build/lib/tests/test_vueengine.py
build/lib/docs/conf.py
build/lib/gdaps_frontend_vue/__init__.py
build/lib/gdaps_frontend_vue/webpack.py
build/lib/tests/__init__.py
build/lib/tests/conftest.py
build/lib/tests/test_settings.py
build/lib/tests/test_vueengine.py
docs/APIs.rst
docs/Contributing.rst
docs/Installation.rst
docs/Makefile
docs/conf.py
docs/index.rst
docs/make.bat
docs/requirements.txt
docs/usage.rst
gdaps_frontend_vue/__init__.py
gdaps_frontend_vue/webpack.py
tests/__init__.py
tests/conftest.py
tests/test_settings.py
tests/test_vueengine.py
gdaps_frontend_vue-0.0.5.dist-info/LICENSE.md
gdaps_frontend_vue-0.0.5.dist-info/METADATA
gdaps_frontend_vue-0.0.5.dist-info/WHEEL
gdaps_frontend_vue-0.0.5.dist-info/entry_points.txt
gdaps_frontend_vue-0.0.5.dist-info/top_level.txt
gdaps_frontend_vue-0.0.5.dist-info/RECORD
